gisglb/__init__.py
gisglb/colors.py
gisglb/dem.py
gisglb/glb.py
gisglb/layers.py
gisglb/main.py
gisglb/utils.py
gisglb-0.1.5.dist-info/METADATA
gisglb-0.1.5.dist-info/WHEEL
gisglb-0.1.5.dist-info/top_level.txt
gisglb-0.1.5.dist-info/RECORD
