Metadata-Version: 2.4
Name: gisglb
Version: 0.1.5
Summary: Create GLB 3D model file from GIS data
Author-email: Nicklas Bystedt <ybin64@gmail.com>
License-Expression: GPL-3.0
Keywords: gis,glb,gltf,3d,dem,terrain,geotiff,rasterio,trimesh
Classifier: Development Status :: 3 - Alpha
Classifier: Intended Audience :: Developers
Classifier: Intended Audience :: Science/Research
Classifier: Programming Language :: Python :: 3.13
Classifier: Topic :: Scientific/Engineering :: GIS
Classifier: Topic :: Multimedia :: Graphics :: 3D Modeling
Requires-Python: >=3.13
Requires-Dist: fast-simplification>=0.1.13
Requires-Dist: geopandas>=1.1.2
Requires-Dist: mapbox-earcut>=1.0.2
Requires-Dist: pillow>=12.0.0
Requires-Dist: rasterio>=1.4.4
Requires-Dist: scipy>=1.16.3
Requires-Dist: trimesh>=4.10.1
